LICENSE
MANIFEST.in
README.rst
requirements.txt
setup.cfg
setup.py
tensorboard_easy/__init__.py
tensorboard_easy/logger.py
tensorboard_easy/utils.py
tensorboard_easy.egg-info/PKG-INFO
tensorboard_easy.egg-info/SOURCES.txt
tensorboard_easy.egg-info/dependency_links.txt
tensorboard_easy.egg-info/requires.txt
tensorboard_easy.egg-info/top_level.txt
tensorboard_easy/proto/README.md
tensorboard_easy/proto/__init__.py
tensorboard_easy/proto/event_pb2.py
tensorboard_easy/proto/summary_pb2.py
tensorboard_easy/proto/tensor_pb2.py
tensorboard_easy/proto/tensor_shape_pb2.py
tensorboard_easy/proto/types_pb2.py
tensorboard_easy/tests/__init__.py
tensorboard_easy/tests/test_logger.py