Metadata-Version: 1.1
Name: tensorboard-easy
Version: 0.2.3
Summary: A tensorflow-independent tensorboard logger
Home-page: https://github.com/maxme1/tensorboard-easy
Author: maxme1
Author-email: maxs987@gmail.com
License: MIT
Download-URL: https://github.com/maxme1/tensorboard-easy/archive/0.2.3.tar.gz
Keywords: tensorboard,logging
Platform: UNKNOWN
Classifier: Development Status :: 5 - Production/Stable
Classifier: Programming Language :: Python :: 3.4
Classifier: Programming Language :: Python :: 3.5
Classifier: Programming Language :: Python :: 3.6
